{"type": "line", "data": {"years": [{"count": 8, "loan_amount": 512, "year": "1996"}, {"count": 13, "loan_amount": 1340, "year": "1997"}, {"count": 12, "loan_amount": 1238, "year": "1998"}, {"count": 17, "loan_amount": 1732, "year": "1999"}, {"count": 11, "loan_amount": 1074, "year": "2000"}, {"count": 21, "loan_amount": 3978, "year": "2001"}, {"count": 74, "loan_amount": 13254, "year": "2002"}, {"count": 109, "loan_amount": 17071, "year": "2003"}, {"count": 114, "loan_amount": 20507, "year": "2004"}, {"count": 75, "loan_amount": 12833, "year": "2005"}, {"count": 72, "loan_amount": 14937, "year": "2006"}, {"count": 41, "loan_amount": 6260, "year": "2007"}, {"count": 86, "loan_amount": 15445, "year": "2008"}, {"count": 83, "loan_amount": 13146, "year": "2009"}, {"count": 91, "loan_amount": 13519, "year": "2010"}]}, "FinancialInstitution": "Colonial Savings Fa", "loanType": "all", "location": "01"}