{"type": "line", "data": {"years": [{"count": 1409, "loan_amount": 13778, "year": "1990"}, {"count": 988, "loan_amount": 9181, "year": "1991"}, {"count": 2787, "loan_amount": 30086, "year": "1992"}, {"count": 2869, "loan_amount": 35978, "year": "1993"}, {"count": 2758, "loan_amount": 30076, "year": "1994"}, {"count": 2435, "loan_amount": 25830, "year": "1995"}, {"count": 2911, "loan_amount": 36115, "year": "1996"}, {"count": 2839, "loan_amount": 37907, "year": "1997"}, {"count": 2781, "loan_amount": 41417, "year": "1998"}, {"count": 2695, "loan_amount": 43498, "year": "1999"}, {"count": 2449, "loan_amount": 40491, "year": "2000"}, {"count": 2621, "loan_amount": 46721, "year": "2001"}, {"count": 2359, "loan_amount": 51056, "year": "2002"}, {"count": 2056, "loan_amount": 54047, "year": "2003"}, {"count": 2031, "loan_amount": 65157, "year": "2004"}, {"count": 2334, "loan_amount": 81463, "year": "2005"}, {"count": 2628, "loan_amount": 97664, "year": "2006"}, {"count": 2624, "loan_amount": 110213, "year": "2007"}, {"count": 2211, "loan_amount": 115906, "year": "2008"}, {"count": 2073, "loan_amount": 139332, "year": "2009"}, {"count": 1769, "loan_amount": 116312, "year": "2010"}, {"count": 1482, "loan_amount": 85144, "year": "2011"}, {"count": 1742, "loan_amount": 199366, "year": "2012"}, {"count": 1652, "loan_amount": 129819, "year": "2013"}, {"count": 1218, "loan_amount": 88682, "year": "2014"}]}, "FinancialInstitution": "All", "loanType": "home-improvement", "location": "46"}