{"type": "line", "data": {"years": [{"count": 1, "loan_amount": 246, "year": "1998"}, {"count": 2, "loan_amount": 268, "year": "1999"}, {"count": 8, "loan_amount": 1129, "year": "2000"}, {"count": 2, "loan_amount": 411, "year": "2001"}, {"count": 1, "loan_amount": 228, "year": "2002"}, {"count": 3, "loan_amount": 665, "year": "2004"}, {"count": 106, "loan_amount": 24967, "year": "2008"}, {"count": 1137, "loan_amount": 250952, "year": "2009"}, {"count": 844, "loan_amount": 189236, "year": "2010"}, {"count": 338, "loan_amount": 73964, "year": "2011"}, {"count": 295, "loan_amount": 70189, "year": "2012"}, {"count": 137, "loan_amount": 30686, "year": "2013"}, {"count": 61, "loan_amount": 13749, "year": "2014"}]}, "FinancialInstitution": "Provident Funding Associates", "loanType": "all", "location": "33"}