{"type": "line", "data": {"years": [{"count": 91, "loan_amount": 9843, "year": "1996"}, {"count": 183, "loan_amount": 17284, "year": "1997"}, {"count": 104, "loan_amount": 10318, "year": "1998"}, {"count": 218, "loan_amount": 22786, "year": "1999"}, {"count": 305, "loan_amount": 18902, "year": "2000"}, {"count": 207, "loan_amount": 45194, "year": "2001"}, {"count": 108, "loan_amount": 53078, "year": "2002"}, {"count": 135, "loan_amount": 51158, "year": "2003"}, {"count": 257, "loan_amount": 21091, "year": "2004"}]}, "FinancialInstitution": "Provident Bank", "loanType": "all", "location": "04"}