{"type": "line", "data": {"years": [{"count": 198, "loan_amount": 11307, "year": "1990"}, {"count": 214, "loan_amount": 11161, "year": "1991"}, {"count": 244, "loan_amount": 14210, "year": "1992"}, {"count": 225, "loan_amount": 13052, "year": "1993"}, {"count": 285, "loan_amount": 20068, "year": "1994"}, {"count": 243, "loan_amount": 21541, "year": "1995"}, {"count": 288, "loan_amount": 25497, "year": "1996"}, {"count": 281, "loan_amount": 24460, "year": "1997"}, {"count": 433, "loan_amount": 45057, "year": "1998"}, {"count": 540, "loan_amount": 58580, "year": "1999"}, {"count": 576, "loan_amount": 67264, "year": "2000"}, {"count": 789, "loan_amount": 93399, "year": "2001"}, {"count": 907, "loan_amount": 110855, "year": "2002"}, {"count": 888, "loan_amount": 110239, "year": "2003"}, {"count": 1349, "loan_amount": 162660, "year": "2004"}, {"count": 1835, "loan_amount": 168934, "year": "2005"}, {"count": 2735, "loan_amount": 328949, "year": "2006"}, {"count": 3028, "loan_amount": 404849, "year": "2007"}, {"count": 2399, "loan_amount": 332084, "year": "2008"}, {"count": 2371, "loan_amount": 320803, "year": "2009"}, {"count": 2298, "loan_amount": 373582, "year": "2010"}, {"count": 0, "loan_amount": 0, "year": "2011"}, {"count": 0, "loan_amount": 0, "year": "2012"}, {"count": 0, "loan_amount": 0, "year": "2013"}, {"count": 0, "loan_amount": 0, "year": "2014"}]}, "FinancialInstitution": "First National Bank Of Omaha", "loanType": "single-family", "location": "nationwide"}