{"type": "line", "data": {"years": [{"count": 2, "loan_amount": 326, "year": "1998"}, {"count": 15, "loan_amount": 1353, "year": "2000"}, {"count": 6, "loan_amount": 555, "year": "2001"}, {"count": 147, "loan_amount": 15317, "year": "2002"}, {"count": 304, "loan_amount": 33666, "year": "2003"}, {"count": 512, "loan_amount": 52923, "year": "2004"}, {"count": 568, "loan_amount": 65456, "year": "2005"}, {"count": 787, "loan_amount": 78915, "year": "2006"}]}, "FinancialInstitution": "Central Pacific Mortgage", "loanType": "all", "location": "21"}