{"type": "line", "data": {"years": [{"count": 483, "loan_amount": 39300, "year": "1993"}, {"count": 552, "loan_amount": 47248, "year": "1994"}, {"count": 614, "loan_amount": 51907, "year": "1995"}, {"count": 733, "loan_amount": 64677, "year": "1996"}, {"count": 718, "loan_amount": 65483, "year": "1997"}, {"count": 908, "loan_amount": 88304, "year": "1998"}, {"count": 773, "loan_amount": 83240, "year": "1999"}, {"count": 617, "loan_amount": 69031, "year": "2000"}, {"count": 780, "loan_amount": 94130, "year": "2001"}, {"count": 940, "loan_amount": 116854, "year": "2002"}, {"count": 993, "loan_amount": 133625, "year": "2003"}, {"count": 836, "loan_amount": 111494, "year": "2004"}, {"count": 712, "loan_amount": 99461, "year": "2005"}, {"count": 686, "loan_amount": 94006, "year": "2006"}, {"count": 590, "loan_amount": 86818, "year": "2007"}]}, "FinancialInstitution": "Hammersmith Financial Lp", "loanType": "single-family", "location": "nationwide"}