{"type": "line", "data": {"years": [{"count": 1, "loan_amount": 131, "year": "1996"}, {"count": 6, "loan_amount": 4084, "year": "2002"}, {"count": 6, "loan_amount": 24112, "year": "2003"}, {"count": 2026, "loan_amount": 542394, "year": "2004"}, {"count": 7379, "loan_amount": 1982438, "year": "2005"}, {"count": 7911, "loan_amount": 2007709, "year": "2006"}, {"count": 9272, "loan_amount": 2546697, "year": "2007"}, {"count": 13658, "loan_amount": 4578872, "year": "2008"}, {"count": 11991, "loan_amount": 3289819, "year": "2009"}, {"count": 13002, "loan_amount": 3866420, "year": "2010"}]}, "FinancialInstitution": "Bank One Na", "loanType": "all", "location": "09"}