{"type": "line", "data": {"years": [{"count": 55, "loan_amount": 8439, "year": "1990"}, {"count": 52, "loan_amount": 9467, "year": "1991"}, {"count": 26, "loan_amount": 4278, "year": "1992"}, {"count": 47, "loan_amount": 7157, "year": "1993"}, {"count": 192, "loan_amount": 34505, "year": "1994"}, {"count": 166, "loan_amount": 27781, "year": "1995"}, {"count": 255, "loan_amount": 50357, "year": "1997"}, {"count": 170, "loan_amount": 37880, "year": "1998"}, {"count": 196, "loan_amount": 42723, "year": "1999"}, {"count": 538, "loan_amount": 109556, "year": "2000"}, {"count": 711, "loan_amount": 97928, "year": "2001"}, {"count": 155, "loan_amount": 34784, "year": "2002"}, {"count": 188, "loan_amount": 53889, "year": "2003"}, {"count": 296, "loan_amount": 107468, "year": "2004"}, {"count": 394, "loan_amount": 154261, "year": "2005"}, {"count": 209, "loan_amount": 99068, "year": "2006"}, {"count": 361, "loan_amount": 254396, "year": "2007"}, {"count": 280, "loan_amount": 167905, "year": "2008"}, {"count": 322, "loan_amount": 155477, "year": "2009"}, {"count": 917, "loan_amount": 455852, "year": "2010"}, {"count": 1921, "loan_amount": 709752, "year": "2011"}, {"count": 2782, "loan_amount": 901701, "year": "2012"}, {"count": 2392, "loan_amount": 906848, "year": "2013"}, {"count": 2636, "loan_amount": 1114939, "year": "2014"}]}, "FinancialInstitution": "Kinecta Federal Credit Union", "loanType": "single-family", "location": "nationwide"}