{"type": "line", "data": {"years": [{"count": 2180, "loan_amount": 243985, "year": "1996"}, {"count": 2313, "loan_amount": 271476, "year": "1997"}, {"count": 3743, "loan_amount": 487509, "year": "1998"}, {"count": 2942, "loan_amount": 392253, "year": "1999"}, {"count": 1681, "loan_amount": 217685, "year": "2000"}, {"count": 4704, "loan_amount": 729733, "year": "2001"}, {"count": 7117, "loan_amount": 1154491, "year": "2002"}, {"count": 10525, "loan_amount": 1869894, "year": "2003"}, {"count": 7028, "loan_amount": 1295920, "year": "2004"}, {"count": 7245, "loan_amount": 1429633, "year": "2005"}, {"count": 4876, "loan_amount": 1040555, "year": "2006"}, {"count": 6023, "loan_amount": 1421585, "year": "2007"}, {"count": 6257, "loan_amount": 1533128, "year": "2008"}, {"count": 4202, "loan_amount": 1057921, "year": "2009"}, {"count": 3672, "loan_amount": 958833, "year": "2010"}]}, "FinancialInstitution": "Flagstar Bank", "loanType": "all", "location": "24"}