{"type": "line", "data": {"years": [{"count": 0, "loan_amount": 0, "year": "1990"}, {"count": 0, "loan_amount": 0, "year": "1991"}, {"count": 0, "loan_amount": 0, "year": "1992"}, {"count": 0, "loan_amount": 0, "year": "1993"}, {"count": 0, "loan_amount": 0, "year": "1994"}, {"count": 0, "loan_amount": 0, "year": "1995"}, {"count": 0, "loan_amount": 0, "year": "1996"}, {"count": 0, "loan_amount": 0, "year": "1997"}, {"count": 0, "loan_amount": 0, "year": "1998"}, {"count": 52, "loan_amount": 8228, "year": "1999"}, {"count": 187, "loan_amount": 38231, "year": "2000"}, {"count": 1812, "loan_amount": 410010, "year": "2001"}, {"count": 2472, "loan_amount": 579158, "year": "2002"}, {"count": 4682, "loan_amount": 1073764, "year": "2003"}, {"count": 2784, "loan_amount": 676473, "year": "2004"}, {"count": 4340, "loan_amount": 1106096, "year": "2005"}, {"count": 5561, "loan_amount": 1347168, "year": "2006"}, {"count": 5645, "loan_amount": 1546297, "year": "2007"}, {"count": 3090, "loan_amount": 857466, "year": "2008"}, {"count": 9801, "loan_amount": 3066065, "year": "2009"}, {"count": 12542, "loan_amount": 4085680, "year": "2010"}, {"count": 12622, "loan_amount": 3998261, "year": "2011"}, {"count": 41716, "loan_amount": 13946378, "year": "2012"}, {"count": 49120, "loan_amount": 15484064, "year": "2013"}, {"count": 28555, "loan_amount": 9140477, "year": "2014"}]}, "FinancialInstitution": "Quicken Loans", "loanType": "refi", "location": "06"}