{"type": "line", "data": {"years": [{"count": 0, "loan_amount": 0, "year": "1990"}, {"count": 208, "loan_amount": 11526, "year": "1991"}, {"count": 502, "loan_amount": 26831, "year": "1992"}, {"count": 485, "loan_amount": 29164, "year": "1993"}, {"count": 294, "loan_amount": 20035, "year": "1994"}, {"count": 181, "loan_amount": 13227, "year": "1995"}, {"count": 395, "loan_amount": 27282, "year": "1996"}, {"count": 482, "loan_amount": 37547, "year": "1997"}, {"count": 639, "loan_amount": 50611, "year": "1998"}, {"count": 925, "loan_amount": 79331, "year": "1999"}, {"count": 723, "loan_amount": 64942, "year": "2000"}, {"count": 906, "loan_amount": 95992, "year": "2001"}, {"count": 1587, "loan_amount": 168436, "year": "2002"}, {"count": 2287, "loan_amount": 249069, "year": "2003"}, {"count": 1725, "loan_amount": 202985, "year": "2004"}, {"count": 1574, "loan_amount": 172048, "year": "2005"}, {"count": 1565, "loan_amount": 177067, "year": "2006"}, {"count": 1162, "loan_amount": 128301, "year": "2007"}, {"count": 1131, "loan_amount": 152443, "year": "2008"}, {"count": 1432, "loan_amount": 202469, "year": "2009"}, {"count": 1482, "loan_amount": 207481, "year": "2010"}, {"count": 1351, "loan_amount": 188982, "year": "2011"}, {"count": 1442, "loan_amount": 201755, "year": "2012"}, {"count": 1368, "loan_amount": 201552, "year": "2013"}, {"count": 1181, "loan_amount": 181766, "year": "2014"}]}, "FinancialInstitution": "First Collinsville Bank", "loanType": "all", "location": "nationwide"}