{"type": "line", "data": {"years": [{"count": 379, "loan_amount": 57268, "year": "1996"}, {"count": 501, "loan_amount": 92846, "year": "1997"}, {"count": 1944, "loan_amount": 284213, "year": "1998"}, {"count": 2118, "loan_amount": 347905, "year": "1999"}, {"count": 2761, "loan_amount": 421790, "year": "2000"}, {"count": 3992, "loan_amount": 642421, "year": "2001"}, {"count": 7784, "loan_amount": 1301102, "year": "2002"}, {"count": 9061, "loan_amount": 1575398, "year": "2003"}, {"count": 6338, "loan_amount": 1253231, "year": "2004"}, {"count": 5975, "loan_amount": 1193634, "year": "2005"}, {"count": 3911, "loan_amount": 730852, "year": "2006"}, {"count": 3449, "loan_amount": 680473, "year": "2007"}, {"count": 2892, "loan_amount": 590271, "year": "2008"}]}, "FinancialInstitution": "Ohio Savings Bank", "loanType": "all", "location": "27"}