{"type": "line", "data": {"years": [{"count": 63, "loan_amount": 2069, "year": "1990"}, {"count": 62, "loan_amount": 2207, "year": "1991"}, {"count": 35, "loan_amount": 918, "year": "1992"}, {"count": 413, "loan_amount": 24098, "year": "1993"}, {"count": 584, "loan_amount": 36043, "year": "1994"}, {"count": 946, "loan_amount": 61520, "year": "1995"}, {"count": 1033, "loan_amount": 71490, "year": "1996"}, {"count": 705, "loan_amount": 47226, "year": "1997"}, {"count": 1543, "loan_amount": 99412, "year": "1998"}, {"count": 791, "loan_amount": 51390, "year": "1999"}, {"count": 837, "loan_amount": 61407, "year": "2000"}, {"count": 884, "loan_amount": 73691, "year": "2001"}, {"count": 1073, "loan_amount": 89932, "year": "2002"}, {"count": 1127, "loan_amount": 90759, "year": "2003"}, {"count": 919, "loan_amount": 83503, "year": "2004"}, {"count": 978, "loan_amount": 101319, "year": "2005"}, {"count": 700, "loan_amount": 74317, "year": "2006"}, {"count": 593, "loan_amount": 66903, "year": "2007"}, {"count": 507, "loan_amount": 59657, "year": "2008"}, {"count": 539, "loan_amount": 63224, "year": "2009"}, {"count": 405, "loan_amount": 48026, "year": "2010"}, {"count": 438, "loan_amount": 53211, "year": "2011"}, {"count": 526, "loan_amount": 67267, "year": "2012"}, {"count": 451, "loan_amount": 63458, "year": "2013"}, {"count": 251, "loan_amount": 36521, "year": "2014"}]}, "FinancialInstitution": "National Bank", "loanType": "all", "location": "nationwide"}