{"type": "line", "data": {"years": [{"count": 44, "loan_amount": 1566, "year": "1994"}, {"count": 195, "loan_amount": 7010, "year": "1995"}, {"count": 242, "loan_amount": 10782, "year": "1996"}, {"count": 711, "loan_amount": 36198, "year": "1997"}, {"count": 966, "loan_amount": 60182, "year": "1998"}, {"count": 887, "loan_amount": 56944, "year": "1999"}, {"count": 1256, "loan_amount": 74868, "year": "2000"}, {"count": 1425, "loan_amount": 109048, "year": "2001"}, {"count": 758, "loan_amount": 68135, "year": "2002"}]}, "FinancialInstitution": "Wachovia Bank Of Delaware", "loanType": "all", "location": "19"}