{"type": "line", "data": {"years": [{"count": 198, "loan_amount": 1526, "year": "1990"}, {"count": 283, "loan_amount": 2115, "year": "1991"}, {"count": 185, "loan_amount": 1258, "year": "1992"}, {"count": 205, "loan_amount": 1873, "year": "1993"}, {"count": 186, "loan_amount": 1777, "year": "1994"}, {"count": 138, "loan_amount": 1286, "year": "1995"}, {"count": 158, "loan_amount": 1766, "year": "1996"}, {"count": 127, "loan_amount": 1593, "year": "1997"}, {"count": 67, "loan_amount": 856, "year": "1998"}, {"count": 95, "loan_amount": 1227, "year": "1999"}, {"count": 95, "loan_amount": 1421, "year": "2000"}, {"count": 114, "loan_amount": 1576, "year": "2001"}, {"count": 90, "loan_amount": 1442, "year": "2002"}, {"count": 75, "loan_amount": 1267, "year": "2003"}, {"count": 113, "loan_amount": 4992, "year": "2004"}, {"count": 170, "loan_amount": 9374, "year": "2005"}, {"count": 138, "loan_amount": 6928, "year": "2006"}, {"count": 121, "loan_amount": 5905, "year": "2007"}, {"count": 111, "loan_amount": 6465, "year": "2008"}, {"count": 78, "loan_amount": 5389, "year": "2009"}, {"count": 90, "loan_amount": 8015, "year": "2010"}, {"count": 56, "loan_amount": 6568, "year": "2011"}, {"count": 79, "loan_amount": 11032, "year": "2012"}, {"count": 40, "loan_amount": 4653, "year": "2013"}, {"count": 32, "loan_amount": 6048, "year": "2014"}]}, "FinancialInstitution": "Southside Bank", "loanType": "home-improvement", "location": "nationwide"}