{"type": "line", "data": {"years": [{"count": 243, "loan_amount": 27026, "year": "1995"}, {"count": 541, "loan_amount": 58859, "year": "1996"}, {"count": 522, "loan_amount": 62696, "year": "1997"}, {"count": 517, "loan_amount": 63088, "year": "1998"}, {"count": 802, "loan_amount": 105853, "year": "1999"}, {"count": 553, "loan_amount": 66636, "year": "2000"}, {"count": 154, "loan_amount": 97677, "year": "2001"}, {"count": 146, "loan_amount": 59304, "year": "2002"}, {"count": 228, "loan_amount": 85521, "year": "2003"}, {"count": 273, "loan_amount": 26028, "year": "2004"}]}, "FinancialInstitution": "Provident Bank", "loanType": "all", "location": "53"}