{"type": "line", "data": {"years": [{"count": 9, "loan_amount": 578, "year": "1991"}, {"count": 265, "loan_amount": 16675, "year": "1993"}, {"count": 41, "loan_amount": 2381, "year": "1994"}, {"count": 8, "loan_amount": 567, "year": "1995"}, {"count": 12, "loan_amount": 800, "year": "1996"}, {"count": 11, "loan_amount": 890, "year": "1997"}, {"count": 71, "loan_amount": 5555, "year": "1998"}, {"count": 31, "loan_amount": 2268, "year": "1999"}, {"count": 23, "loan_amount": 2768, "year": "2000"}, {"count": 121, "loan_amount": 15850, "year": "2001"}, {"count": 481, "loan_amount": 65094, "year": "2002"}, {"count": 2099, "loan_amount": 263121, "year": "2003"}, {"count": 1038, "loan_amount": 165696, "year": "2004"}, {"count": 702, "loan_amount": 94950, "year": "2005"}, {"count": 515, "loan_amount": 74064, "year": "2006"}, {"count": 456, "loan_amount": 71793, "year": "2007"}, {"count": 275, "loan_amount": 48244, "year": "2008"}, {"count": 1431, "loan_amount": 259760, "year": "2009"}]}, "FinancialInstitution": "Homeowners Mortgage Enterprise", "loanType": "refi", "location": "nationwide"}