{"type": "line", "data": {"years": [{"count": 99, "loan_amount": 1297, "year": "1999"}, {"count": 130, "loan_amount": 1414, "year": "2000"}, {"count": 132, "loan_amount": 1747, "year": "2001"}, {"count": 190, "loan_amount": 2313, "year": "2002"}, {"count": 233, "loan_amount": 3022, "year": "2003"}, {"count": 318, "loan_amount": 6862, "year": "2004"}, {"count": 382, "loan_amount": 9531, "year": "2005"}, {"count": 504, "loan_amount": 11190, "year": "2006"}, {"count": 540, "loan_amount": 12845, "year": "2007"}, {"count": 545, "loan_amount": 19378, "year": "2008"}, {"count": 510, "loan_amount": 14405, "year": "2009"}, {"count": 399, "loan_amount": 10359, "year": "2010"}, {"count": 242, "loan_amount": 4886, "year": "2011"}, {"count": 179, "loan_amount": 4753, "year": "2012"}, {"count": 225, "loan_amount": 9174, "year": "2013"}, {"count": 205, "loan_amount": 6378, "year": "2014"}]}, "FinancialInstitution": "New Peoples Bank Inc", "loanType": "home-improvement", "location": "nationwide"}