{"type": "line", "data": {"years": [{"count": 80, "loan_amount": 13957, "year": "1998"}, {"count": 583, "loan_amount": 97675, "year": "1999"}, {"count": 1802, "loan_amount": 312324, "year": "2000"}, {"count": 2306, "loan_amount": 451623, "year": "2001"}, {"count": 2548, "loan_amount": 570170, "year": "2002"}, {"count": 2620, "loan_amount": 594427, "year": "2003"}, {"count": 2031, "loan_amount": 528238, "year": "2004"}, {"count": 1711, "loan_amount": 477915, "year": "2005"}, {"count": 2125, "loan_amount": 576827, "year": "2006"}, {"count": 3409, "loan_amount": 942309, "year": "2007"}, {"count": 2824, "loan_amount": 786161, "year": "2008"}, {"count": 6275, "loan_amount": 1732130, "year": "2009"}, {"count": 6006, "loan_amount": 1698918, "year": "2010"}, {"count": 3231, "loan_amount": 902215, "year": "2011"}, {"count": 4063, "loan_amount": 1137311, "year": "2012"}, {"count": 1676, "loan_amount": 471458, "year": "2013"}, {"count": 500, "loan_amount": 144872, "year": "2014"}]}, "FinancialInstitution": "Provident Funding Associates", "loanType": "all", "location": "25"}