{"type": "line", "data": {"years": [{"count": 508, "loan_amount": 34559, "year": "1990"}, {"count": 792, "loan_amount": 64100, "year": "1991"}, {"count": 1427, "loan_amount": 148187, "year": "1992"}, {"count": 1260, "loan_amount": 134824, "year": "1993"}, {"count": 1309, "loan_amount": 185601, "year": "1994"}, {"count": 1504, "loan_amount": 307634, "year": "1995"}, {"count": 1964, "loan_amount": 319346, "year": "1996"}, {"count": 2026, "loan_amount": 443743, "year": "1997"}, {"count": 1375, "loan_amount": 430585, "year": "1998"}, {"count": 1060, "loan_amount": 154025, "year": "1999"}, {"count": 956, "loan_amount": 271195, "year": "2000"}, {"count": 1394, "loan_amount": 240372, "year": "2001"}, {"count": 1872, "loan_amount": 501540, "year": "2002"}, {"count": 1900, "loan_amount": 518747, "year": "2003"}, {"count": 1903, "loan_amount": 872649, "year": "2004"}, {"count": 1546, "loan_amount": 405568, "year": "2005"}]}, "FinancialInstitution": "Regency Savings Bank", "loanType": "all", "location": "nationwide"}