{"type": "line", "data": {"years": [{"count": 1172, "loan_amount": 26899, "year": "1990"}, {"count": 708, "loan_amount": 28207, "year": "1991"}, {"count": 894, "loan_amount": 15401, "year": "1992"}, {"count": 2471, "loan_amount": 89117, "year": "1993"}, {"count": 2815, "loan_amount": 50698, "year": "1994"}, {"count": 2801, "loan_amount": 47437, "year": "1995"}, {"count": 3052, "loan_amount": 52596, "year": "1996"}, {"count": 3611, "loan_amount": 72802, "year": "1997"}, {"count": 3498, "loan_amount": 82389, "year": "1998"}, {"count": 4238, "loan_amount": 107935, "year": "1999"}, {"count": 4537, "loan_amount": 113217, "year": "2000"}, {"count": 5309, "loan_amount": 179519, "year": "2001"}, {"count": 4474, "loan_amount": 183020, "year": "2002"}, {"count": 4011, "loan_amount": 223324, "year": "2003"}, {"count": 6736, "loan_amount": 512500, "year": "2004"}, {"count": 7248, "loan_amount": 588814, "year": "2005"}, {"count": 8784, "loan_amount": 608397, "year": "2006"}, {"count": 6615, "loan_amount": 516412, "year": "2007"}, {"count": 3295, "loan_amount": 265832, "year": "2008"}, {"count": 2174, "loan_amount": 206448, "year": "2009"}, {"count": 1973, "loan_amount": 214078, "year": "2010"}, {"count": 1896, "loan_amount": 187254, "year": "2011"}, {"count": 2135, "loan_amount": 241832, "year": "2012"}, {"count": 2348, "loan_amount": 290564, "year": "2013"}, {"count": 2055, "loan_amount": 226673, "year": "2014"}]}, "FinancialInstitution": "All", "loanType": "home-improvement", "location": "33"}