{"type": "line", "data": {"years": [{"count": 632, "loan_amount": 24328, "year": "1990"}, {"count": 707, "loan_amount": 29824, "year": "1991"}, {"count": 764, "loan_amount": 44819, "year": "1992"}, {"count": 822, "loan_amount": 47097, "year": "1993"}, {"count": 778, "loan_amount": 42759, "year": "1994"}, {"count": 642, "loan_amount": 33757, "year": "1995"}, {"count": 590, "loan_amount": 30262, "year": "1996"}, {"count": 608, "loan_amount": 35081, "year": "1997"}, {"count": 542, "loan_amount": 34562, "year": "1998"}, {"count": 557, "loan_amount": 42375, "year": "1999"}, {"count": 514, "loan_amount": 33244, "year": "2000"}, {"count": 569, "loan_amount": 41672, "year": "2001"}, {"count": 718, "loan_amount": 171564, "year": "2002"}, {"count": 815, "loan_amount": 71780, "year": "2003"}, {"count": 576, "loan_amount": 39928, "year": "2004"}, {"count": 416, "loan_amount": 38311, "year": "2005"}, {"count": 350, "loan_amount": 23387, "year": "2006"}, {"count": 423, "loan_amount": 29870, "year": "2007"}, {"count": 452, "loan_amount": 46621, "year": "2008"}, {"count": 572, "loan_amount": 62973, "year": "2009"}, {"count": 512, "loan_amount": 52820, "year": "2010"}, {"count": 430, "loan_amount": 41641, "year": "2011"}, {"count": 526, "loan_amount": 51836, "year": "2012"}, {"count": 516, "loan_amount": 57598, "year": "2013"}, {"count": 426, "loan_amount": 49435, "year": "2014"}]}, "FinancialInstitution": "The Security National Bank Of", "loanType": "all", "location": "nationwide"}