{"type": "line", "data": {"years": [{"count": 3038, "loan_amount": 304024, "year": "1994"}, {"count": 1440, "loan_amount": 159770, "year": "1995"}, {"count": 1170, "loan_amount": 148926, "year": "1996"}, {"count": 1292, "loan_amount": 158348, "year": "1997"}, {"count": 1314, "loan_amount": 166668, "year": "1998"}, {"count": 1556, "loan_amount": 206207, "year": "1999"}, {"count": 1451, "loan_amount": 202201, "year": "2000"}, {"count": 1653, "loan_amount": 236313, "year": "2001"}, {"count": 2333, "loan_amount": 374860, "year": "2002"}, {"count": 3847, "loan_amount": 606850, "year": "2003"}, {"count": 2362, "loan_amount": 355789, "year": "2004"}, {"count": 4258, "loan_amount": 830669, "year": "2005"}, {"count": 7212, "loan_amount": 1500106, "year": "2006"}, {"count": 7413, "loan_amount": 1627742, "year": "2007"}, {"count": 4120, "loan_amount": 881806, "year": "2008"}, {"count": 1767, "loan_amount": 349107, "year": "2009"}, {"count": 1167, "loan_amount": 235318, "year": "2010"}]}, "FinancialInstitution": "Pulte Mortgage Corporation", "loanType": "all", "location": "04"}