{"type": "line", "data": {"years": [{"count": 2460, "loan_amount": 164799, "year": "1990"}, {"count": 4889, "loan_amount": 386903, "year": "1991"}, {"count": 5827, "loan_amount": 499441, "year": "1992"}, {"count": 6560, "loan_amount": 574455, "year": "1993"}, {"count": 4307, "loan_amount": 378597, "year": "1994"}, {"count": 4950, "loan_amount": 489670, "year": "1995"}, {"count": 4997, "loan_amount": 510591, "year": "1996"}, {"count": 4286, "loan_amount": 464910, "year": "1997"}, {"count": 6985, "loan_amount": 821364, "year": "1998"}, {"count": 5287, "loan_amount": 681069, "year": "1999"}, {"count": 3690, "loan_amount": 528662, "year": "2000"}, {"count": 8600, "loan_amount": 1310287, "year": "2001"}, {"count": 9301, "loan_amount": 1483261, "year": "2002"}, {"count": 8279, "loan_amount": 1329093, "year": "2003"}, {"count": 4402, "loan_amount": 704437, "year": "2004"}, {"count": 3414, "loan_amount": 582857, "year": "2005"}, {"count": 3888, "loan_amount": 652079, "year": "2006"}, {"count": 3852, "loan_amount": 657293, "year": "2007"}, {"count": 6156, "loan_amount": 1063506, "year": "2008"}, {"count": 8549, "loan_amount": 1588300, "year": "2009"}, {"count": 6429, "loan_amount": 1224796, "year": "2010"}, {"count": 4683, "loan_amount": 899324, "year": "2011"}, {"count": 0, "loan_amount": 0, "year": "2012"}, {"count": 0, "loan_amount": 0, "year": "2013"}, {"count": 0, "loan_amount": 0, "year": "2014"}]}, "FinancialInstitution": "Universal Lending Corp", "loanType": "all", "location": "nationwide"}