{"type": "line", "data": {"years": [{"count": 85, "loan_amount": 1439, "year": "1990"}, {"count": 87, "loan_amount": 764, "year": "1991"}, {"count": 86, "loan_amount": 690, "year": "1992"}, {"count": 82, "loan_amount": 527, "year": "1993"}, {"count": 90, "loan_amount": 781, "year": "1994"}, {"count": 93, "loan_amount": 1064, "year": "1995"}, {"count": 242, "loan_amount": 1884, "year": "1996"}, {"count": 90, "loan_amount": 787, "year": "1997"}, {"count": 80, "loan_amount": 846, "year": "1998"}, {"count": 139, "loan_amount": 1296, "year": "1999"}, {"count": 118, "loan_amount": 1945, "year": "2000"}, {"count": 101, "loan_amount": 1362, "year": "2001"}, {"count": 99, "loan_amount": 1682, "year": "2002"}, {"count": 115, "loan_amount": 1605, "year": "2003"}, {"count": 62, "loan_amount": 513, "year": "2004"}, {"count": 84, "loan_amount": 1014, "year": "2005"}, {"count": 114, "loan_amount": 2753, "year": "2006"}, {"count": 180, "loan_amount": 5254, "year": "2007"}, {"count": 80, "loan_amount": 1960, "year": "2008"}, {"count": 35, "loan_amount": 792, "year": "2009"}, {"count": 20, "loan_amount": 290, "year": "2010"}, {"count": 9, "loan_amount": 124, "year": "2011"}, {"count": 16, "loan_amount": 1295, "year": "2012"}, {"count": 19, "loan_amount": 1392, "year": "2013"}, {"count": 30, "loan_amount": 2048, "year": "2014"}]}, "FinancialInstitution": "Old Second National Bank", "loanType": "home-improvement", "location": "nationwide"}