{"type": "line", "data": {"years": [{"count": 5, "loan_amount": 537, "year": "1990"}, {"count": 17031, "loan_amount": 110012, "year": "1991"}, {"count": 18286, "loan_amount": 102242, "year": "1992"}, {"count": 15648, "loan_amount": 101542, "year": "1993"}, {"count": 10194, "loan_amount": 81991, "year": "1994"}, {"count": 8273, "loan_amount": 71522, "year": "1995"}, {"count": 12032, "loan_amount": 125711, "year": "1996"}, {"count": 14218, "loan_amount": 142313, "year": "1997"}, {"count": 11405, "loan_amount": 114699, "year": "1998"}, {"count": 11969, "loan_amount": 111362, "year": "1999"}, {"count": 10129, "loan_amount": 96543, "year": "2000"}, {"count": 8305, "loan_amount": 75613, "year": "2001"}, {"count": 7377, "loan_amount": 67537, "year": "2002"}, {"count": 8237, "loan_amount": 84189, "year": "2003"}, {"count": 10003, "loan_amount": 113959, "year": "2004"}, {"count": 11340, "loan_amount": 134762, "year": "2005"}, {"count": 9289, "loan_amount": 112221, "year": "2006"}, {"count": 7862, "loan_amount": 94562, "year": "2007"}, {"count": 6269, "loan_amount": 74937, "year": "2008"}, {"count": 4886, "loan_amount": 54601, "year": "2009"}, {"count": 4892, "loan_amount": 54180, "year": "2010"}]}, "FinancialInstitution": "Banco Popular De Puerto Rico", "loanType": "home-improvement", "location": "nationwide"}