{"type": "line", "data": {"years": [{"count": 143, "loan_amount": 29128, "year": "2001"}, {"count": 168, "loan_amount": 33584, "year": "2002"}, {"count": 266, "loan_amount": 55740, "year": "2003"}, {"count": 134, "loan_amount": 27901, "year": "2004"}, {"count": 93, "loan_amount": 22022, "year": "2005"}, {"count": 57, "loan_amount": 13994, "year": "2006"}, {"count": 60, "loan_amount": 17017, "year": "2007"}, {"count": 8, "loan_amount": 1729, "year": "2008"}, {"count": 2, "loan_amount": 502, "year": "2009"}, {"count": 3, "loan_amount": 497, "year": "2010"}]}, "FinancialInstitution": "E*Trade Bank", "loanType": "all", "location": "44"}