{"type": "line", "data": {"years": [{"count": 61, "loan_amount": 11583, "year": "1998"}, {"count": 70, "loan_amount": 5889, "year": "1999"}, {"count": 112, "loan_amount": 10661, "year": "2000"}, {"count": 102, "loan_amount": 9109, "year": "2001"}, {"count": 89, "loan_amount": 8318, "year": "2002"}, {"count": 112, "loan_amount": 10708, "year": "2003"}, {"count": 121, "loan_amount": 12279, "year": "2004"}, {"count": 194, "loan_amount": 18393, "year": "2005"}, {"count": 135, "loan_amount": 12538, "year": "2006"}, {"count": 145, "loan_amount": 13956, "year": "2007"}, {"count": 155, "loan_amount": 16987, "year": "2008"}, {"count": 153, "loan_amount": 15957, "year": "2009"}, {"count": 161, "loan_amount": 16116, "year": "2010"}, {"count": 111, "loan_amount": 13522, "year": "2011"}, {"count": 187, "loan_amount": 24407, "year": "2012"}, {"count": 236, "loan_amount": 32430, "year": "2013"}, {"count": 249, "loan_amount": 34334, "year": "2014"}]}, "FinancialInstitution": "Centra Credit Union", "loanType": "single-family", "location": "nationwide"}