{"type": "line", "data": {"years": [{"count": 316, "loan_amount": 21620, "year": "1990"}, {"count": 300, "loan_amount": 22456, "year": "1991"}, {"count": 314, "loan_amount": 26920, "year": "1992"}, {"count": 301, "loan_amount": 25340, "year": "1993"}, {"count": 281, "loan_amount": 24206, "year": "1994"}, {"count": 104, "loan_amount": 7411, "year": "1995"}, {"count": 127, "loan_amount": 9217, "year": "1996"}, {"count": 135, "loan_amount": 11856, "year": "1997"}, {"count": 315, "loan_amount": 31620, "year": "1998"}, {"count": 422, "loan_amount": 50887, "year": "1999"}, {"count": 407, "loan_amount": 48396, "year": "2000"}, {"count": 435, "loan_amount": 53873, "year": "2001"}, {"count": 421, "loan_amount": 55713, "year": "2002"}, {"count": 377, "loan_amount": 54601, "year": "2003"}, {"count": 220, "loan_amount": 36406, "year": "2004"}, {"count": 257, "loan_amount": 44703, "year": "2005"}, {"count": 199, "loan_amount": 37791, "year": "2006"}, {"count": 205, "loan_amount": 39759, "year": "2007"}, {"count": 178, "loan_amount": 35792, "year": "2008"}, {"count": 197, "loan_amount": 33508, "year": "2009"}, {"count": 252, "loan_amount": 47297, "year": "2010"}]}, "FinancialInstitution": "Security Federal Bank", "loanType": "single-family", "location": "nationwide"}