{"type": "line", "data": {"years": [{"count": 170, "loan_amount": 5441, "year": "1990"}, {"count": 178, "loan_amount": 6725, "year": "1991"}, {"count": 253, "loan_amount": 13561, "year": "1992"}, {"count": 278, "loan_amount": 10723, "year": "1993"}, {"count": 239, "loan_amount": 11464, "year": "1994"}, {"count": 249, "loan_amount": 10407, "year": "1995"}, {"count": 276, "loan_amount": 11086, "year": "1996"}, {"count": 255, "loan_amount": 11245, "year": "1997"}, {"count": 1092, "loan_amount": 86779, "year": "1998"}, {"count": 546, "loan_amount": 36611, "year": "1999"}, {"count": 528, "loan_amount": 37796, "year": "2000"}, {"count": 785, "loan_amount": 65894, "year": "2001"}, {"count": 578, "loan_amount": 53982, "year": "2002"}, {"count": 1883, "loan_amount": 185606, "year": "2003"}, {"count": 927, "loan_amount": 79929, "year": "2004"}, {"count": 1122, "loan_amount": 107569, "year": "2005"}, {"count": 1003, "loan_amount": 104958, "year": "2006"}, {"count": 1140, "loan_amount": 116761, "year": "2007"}, {"count": 1480, "loan_amount": 167015, "year": "2008"}, {"count": 2414, "loan_amount": 302444, "year": "2009"}, {"count": 1961, "loan_amount": 246612, "year": "2010"}, {"count": 1499, "loan_amount": 172177, "year": "2011"}, {"count": 2253, "loan_amount": 269785, "year": "2012"}, {"count": 1463, "loan_amount": 169453, "year": "2013"}, {"count": 951, "loan_amount": 97428, "year": "2014"}]}, "FinancialInstitution": "Blackhawk State Bank", "loanType": "all", "location": "nationwide"}