{"type": "line", "data": {"years": [{"count": 476, "loan_amount": 30183, "year": "1998"}, {"count": 286, "loan_amount": 12813, "year": "1999"}, {"count": 434, "loan_amount": 17114, "year": "2000"}, {"count": 583, "loan_amount": 29798, "year": "2001"}, {"count": 478, "loan_amount": 38646, "year": "2002"}, {"count": 727, "loan_amount": 76870, "year": "2003"}, {"count": 332, "loan_amount": 33939, "year": "2004"}, {"count": 345, "loan_amount": 32680, "year": "2005"}, {"count": 123, "loan_amount": 20769, "year": "2006"}, {"count": 105, "loan_amount": 16884, "year": "2007"}, {"count": 143, "loan_amount": 23197, "year": "2008"}, {"count": 228, "loan_amount": 34165, "year": "2009"}, {"count": 307, "loan_amount": 43663, "year": "2010"}, {"count": 187, "loan_amount": 26531, "year": "2011"}, {"count": 299, "loan_amount": 47235, "year": "2012"}, {"count": 292, "loan_amount": 40934, "year": "2013"}, {"count": 125, "loan_amount": 13317, "year": "2014"}]}, "FinancialInstitution": "Northeast Credit Union", "loanType": "refi", "location": "nationwide"}