{"type": "line", "data": {"years": [{"count": 1, "loan_amount": 415, "year": "1993"}, {"count": 1, "loan_amount": 80, "year": "1996"}, {"count": 7, "loan_amount": 1430, "year": "1999"}, {"count": 21, "loan_amount": 4919, "year": "2000"}, {"count": 6, "loan_amount": 2311, "year": "2001"}, {"count": 7, "loan_amount": 1968, "year": "2002"}, {"count": 8, "loan_amount": 2432, "year": "2003"}, {"count": 1, "loan_amount": 334, "year": "2004"}, {"count": 1, "loan_amount": 210, "year": "2005"}, {"count": 1, "loan_amount": 347, "year": "2007"}]}, "FinancialInstitution": "Midamerica Bank Fsb", "loanType": "all", "location": "34"}