{"type": "line", "data": {"years": [{"count": 3, "loan_amount": 283, "year": "1991"}, {"count": 17, "loan_amount": 1361, "year": "1992"}, {"count": 10, "loan_amount": 1075, "year": "1993"}, {"count": 13, "loan_amount": 1101, "year": "1994"}, {"count": 16, "loan_amount": 1659, "year": "1995"}, {"count": 16, "loan_amount": 1711, "year": "1996"}, {"count": 131, "loan_amount": 12901, "year": "1997"}, {"count": 1099, "loan_amount": 104441, "year": "1998"}, {"count": 1034, "loan_amount": 101168, "year": "1999"}, {"count": 772, "loan_amount": 78047, "year": "2000"}, {"count": 2777, "loan_amount": 243873, "year": "2001"}, {"count": 3313, "loan_amount": 300562, "year": "2002"}, {"count": 4370, "loan_amount": 459843, "year": "2003"}, {"count": 3812, "loan_amount": 374656, "year": "2004"}, {"count": 4371, "loan_amount": 522442, "year": "2005"}, {"count": 3497, "loan_amount": 501332, "year": "2006"}, {"count": 3926, "loan_amount": 617996, "year": "2007"}, {"count": 2610, "loan_amount": 454031, "year": "2008"}, {"count": 1475, "loan_amount": 259546, "year": "2009"}, {"count": 1688, "loan_amount": 284403, "year": "2010"}]}, "FinancialInstitution": "Gmac Mortgage", "loanType": "all", "location": "16"}