{"type": "line", "data": {"years": [{"count": 7, "loan_amount": 39517, "year": "1990"}, {"count": 3, "loan_amount": 131, "year": "1991"}, {"count": 3, "loan_amount": 109, "year": "1992"}, {"count": 2, "loan_amount": 222, "year": "1995"}, {"count": 1, "loan_amount": 79, "year": "1996"}, {"count": 1817, "loan_amount": 269538, "year": "1997"}, {"count": 1840, "loan_amount": 221048, "year": "1998"}, {"count": 575, "loan_amount": 63993, "year": "1999"}, {"count": 498, "loan_amount": 85872, "year": "2000"}, {"count": 4978, "loan_amount": 707754, "year": "2001"}, {"count": 3522, "loan_amount": 531026, "year": "2002"}, {"count": 5370, "loan_amount": 802394, "year": "2003"}, {"count": 1809, "loan_amount": 343518, "year": "2004"}, {"count": 23319, "loan_amount": 4382157, "year": "2005"}, {"count": 21854, "loan_amount": 4477893, "year": "2006"}, {"count": 15959, "loan_amount": 3882950, "year": "2007"}]}, "FinancialInstitution": "Washington Mutual Bank Fa", "loanType": "all", "location": "41"}