{"type": "line", "data": {"years": [{"count": 7, "loan_amount": 1021, "year": "1997"}, {"count": 96, "loan_amount": 15763, "year": "1998"}, {"count": 205, "loan_amount": 26542, "year": "1999"}, {"count": 217, "loan_amount": 37232, "year": "2000"}, {"count": 239, "loan_amount": 38113, "year": "2001"}, {"count": 210, "loan_amount": 32730, "year": "2002"}, {"count": 229, "loan_amount": 42232, "year": "2003"}, {"count": 447, "loan_amount": 103259, "year": "2004"}, {"count": 1293, "loan_amount": 334327, "year": "2005"}, {"count": 645, "loan_amount": 187103, "year": "2006"}, {"count": 237, "loan_amount": 74844, "year": "2007"}]}, "FinancialInstitution": "Downey Savings And Loan Assoc", "loanType": "all", "location": "32"}