{"type": "line", "data": {"years": [{"count": 452, "loan_amount": 72631, "year": "1992"}, {"count": 284, "loan_amount": 44386, "year": "1993"}, {"count": 233, "loan_amount": 37626, "year": "1994"}, {"count": 306, "loan_amount": 54177, "year": "1995"}, {"count": 456, "loan_amount": 89613, "year": "1996"}, {"count": 545, "loan_amount": 116231, "year": "1997"}, {"count": 337, "loan_amount": 73337, "year": "1998"}, {"count": 337, "loan_amount": 78576, "year": "1999"}, {"count": 368, "loan_amount": 94576, "year": "2000"}, {"count": 291, "loan_amount": 89408, "year": "2001"}, {"count": 315, "loan_amount": 86147, "year": "2002"}, {"count": 283, "loan_amount": 82607, "year": "2003"}, {"count": 310, "loan_amount": 94559, "year": "2004"}, {"count": 247, "loan_amount": 82225, "year": "2005"}, {"count": 193, "loan_amount": 61673, "year": "2006"}, {"count": 187, "loan_amount": 60137, "year": "2007"}, {"count": 209, "loan_amount": 82839, "year": "2008"}, {"count": 192, "loan_amount": 62221, "year": "2009"}, {"count": 208, "loan_amount": 70426, "year": "2010"}, {"count": 183, "loan_amount": 66465, "year": "2011"}, {"count": 209, "loan_amount": 82821, "year": "2012"}, {"count": 232, "loan_amount": 90751, "year": "2013"}, {"count": 181, "loan_amount": 59204, "year": "2014"}]}, "FinancialInstitution": "Middlesex Savings Bank", "loanType": "single-family", "location": "nationwide"}