{"type": "line", "data": {"years": [{"count": 253, "loan_amount": 31631, "year": "2000"}, {"count": 304, "loan_amount": 42327, "year": "2001"}, {"count": 338, "loan_amount": 49058, "year": "2002"}, {"count": 313, "loan_amount": 48917, "year": "2003"}, {"count": 297, "loan_amount": 49331, "year": "2004"}, {"count": 319, "loan_amount": 59020, "year": "2005"}, {"count": 425, "loan_amount": 85012, "year": "2006"}, {"count": 264, "loan_amount": 61615, "year": "2007"}, {"count": 174, "loan_amount": 39117, "year": "2008"}, {"count": 124, "loan_amount": 23531, "year": "2009"}, {"count": 7, "loan_amount": 830, "year": "2010"}, {"count": 46, "loan_amount": 6748, "year": "2011"}, {"count": 110, "loan_amount": 22274, "year": "2012"}, {"count": 181, "loan_amount": 36388, "year": "2013"}, {"count": 165, "loan_amount": 33161, "year": "2014"}]}, "FinancialInstitution": "Bank Of The Cascades", "loanType": "single-family", "location": "nationwide"}