{"type": "line", "data": {"years": [{"count": 3, "loan_amount": 313, "year": "2000"}, {"count": 2, "loan_amount": 250, "year": "2002"}, {"count": 6, "loan_amount": 927, "year": "2003"}, {"count": 2, "loan_amount": 188, "year": "2004"}, {"count": 3, "loan_amount": 581, "year": "2005"}, {"count": 2, "loan_amount": 249, "year": "2007"}, {"count": 3, "loan_amount": 905, "year": "2008"}, {"count": 2, "loan_amount": 289, "year": "2009"}, {"count": 3, "loan_amount": 1041, "year": "2010"}, {"count": 3, "loan_amount": 570, "year": "2011"}, {"count": 2, "loan_amount": 676, "year": "2012"}, {"count": 1, "loan_amount": 270, "year": "2013"}]}, "FinancialInstitution": "Old National Bank", "loanType": "all", "location": "37"}