{"type": "line", "data": {"years": [{"count": 3722, "loan_amount": 243629, "year": "1990"}, {"count": 7181, "loan_amount": 470703, "year": "1991"}, {"count": 22753, "loan_amount": 1664401, "year": "1992"}, {"count": 37934, "loan_amount": 3036765, "year": "1993"}, {"count": 14858, "loan_amount": 1057770, "year": "1994"}, {"count": 8908, "loan_amount": 669273, "year": "1995"}, {"count": 18121, "loan_amount": 1310654, "year": "1996"}, {"count": 21255, "loan_amount": 1627009, "year": "1997"}, {"count": 50662, "loan_amount": 4402724, "year": "1998"}, {"count": 36175, "loan_amount": 2983610, "year": "1999"}, {"count": 20923, "loan_amount": 1690063, "year": "2000"}, {"count": 64914, "loan_amount": 7086779, "year": "2001"}, {"count": 79335, "loan_amount": 9370929, "year": "2002"}, {"count": 109700, "loan_amount": 13018302, "year": "2003"}, {"count": 53829, "loan_amount": 6072051, "year": "2004"}, {"count": 45436, "loan_amount": 5420695, "year": "2005"}, {"count": 37054, "loan_amount": 4322884, "year": "2006"}, {"count": 33602, "loan_amount": 4130055, "year": "2007"}, {"count": 32743, "loan_amount": 5972902, "year": "2008"}, {"count": 55786, "loan_amount": 8902991, "year": "2009"}, {"count": 52011, "loan_amount": 8281569, "year": "2010"}, {"count": 39684, "loan_amount": 6374450, "year": "2011"}, {"count": 53683, "loan_amount": 8717008, "year": "2012"}, {"count": 39946, "loan_amount": 6009493, "year": "2013"}, {"count": 19041, "loan_amount": 2925663, "year": "2014"}]}, "FinancialInstitution": "All", "loanType": "refi", "location": "20"}