{"type": "line", "data": {"years": [{"count": 225, "loan_amount": 17263, "year": "1990"}, {"count": 13, "loan_amount": 1014, "year": "1991"}, {"count": 632, "loan_amount": 60729, "year": "1992"}, {"count": 302, "loan_amount": 25763, "year": "1993"}, {"count": 19, "loan_amount": 1234, "year": "1994"}, {"count": 11, "loan_amount": 819, "year": "1995"}, {"count": 10, "loan_amount": 802, "year": "1996"}, {"count": 10, "loan_amount": 607, "year": "1997"}, {"count": 558, "loan_amount": 54269, "year": "1998"}, {"count": 413, "loan_amount": 37890, "year": "1999"}, {"count": 349, "loan_amount": 27002, "year": "2000"}, {"count": 687, "loan_amount": 67539, "year": "2001"}, {"count": 921, "loan_amount": 98497, "year": "2002"}, {"count": 938, "loan_amount": 122012, "year": "2003"}, {"count": 489, "loan_amount": 87617, "year": "2004"}, {"count": 435, "loan_amount": 78552, "year": "2005"}, {"count": 384, "loan_amount": 62476, "year": "2006"}, {"count": 393, "loan_amount": 71700, "year": "2007"}, {"count": 418, "loan_amount": 98371, "year": "2008"}, {"count": 529, "loan_amount": 119681, "year": "2009"}, {"count": 490, "loan_amount": 110401, "year": "2010"}]}, "FinancialInstitution": "Navy Federal Credit Union", "loanType": "all", "location": "44"}