{"type": "line", "data": {"years": [{"count": 61, "loan_amount": 8092, "year": "1995"}, {"count": 107, "loan_amount": 14520, "year": "1996"}, {"count": 241, "loan_amount": 34040, "year": "1997"}, {"count": 83, "loan_amount": 11965, "year": "1998"}, {"count": 77, "loan_amount": 10605, "year": "1999"}, {"count": 43, "loan_amount": 16559, "year": "2000"}, {"count": 19, "loan_amount": 11915, "year": "2001"}, {"count": 63, "loan_amount": 25024, "year": "2002"}, {"count": 54, "loan_amount": 20808, "year": "2003"}, {"count": 195, "loan_amount": 23481, "year": "2004"}]}, "FinancialInstitution": "Provident Bank", "loanType": "all", "location": "32"}