{"type": "line", "data": {"years": [{"count": 244, "loan_amount": 17880, "year": "1994"}, {"count": 213, "loan_amount": 16645, "year": "1995"}, {"count": 261, "loan_amount": 19835, "year": "1996"}, {"count": 253, "loan_amount": 21708, "year": "1997"}, {"count": 588, "loan_amount": 53256, "year": "1998"}, {"count": 238, "loan_amount": 21628, "year": "1999"}, {"count": 181, "loan_amount": 16024, "year": "2000"}, {"count": 526, "loan_amount": 53114, "year": "2001"}, {"count": 759, "loan_amount": 82205, "year": "2002"}, {"count": 1214, "loan_amount": 133562, "year": "2003"}, {"count": 616, "loan_amount": 79359, "year": "2004"}, {"count": 477, "loan_amount": 73255, "year": "2005"}, {"count": 293, "loan_amount": 46681, "year": "2006"}, {"count": 275, "loan_amount": 46460, "year": "2007"}, {"count": 467, "loan_amount": 64812, "year": "2008"}, {"count": 1019, "loan_amount": 139687, "year": "2009"}, {"count": 728, "loan_amount": 101252, "year": "2010"}, {"count": 521, "loan_amount": 73836, "year": "2011"}, {"count": 655, "loan_amount": 85305, "year": "2012"}, {"count": 515, "loan_amount": 71623, "year": "2013"}, {"count": 278, "loan_amount": 37244, "year": "2014"}]}, "FinancialInstitution": "First South Bank", "loanType": "purchased-loan", "location": "nationwide"}