{"type": "line", "data": {"years": [{"count": 11, "loan_amount": 580, "year": "1990"}, {"count": 44, "loan_amount": 2585, "year": "1991"}, {"count": 481, "loan_amount": 29471, "year": "1992"}, {"count": 2379, "loan_amount": 188185, "year": "1993"}, {"count": 530, "loan_amount": 35092, "year": "1994"}, {"count": 400, "loan_amount": 30449, "year": "1995"}, {"count": 536, "loan_amount": 38780, "year": "1996"}, {"count": 264, "loan_amount": 19493, "year": "1997"}, {"count": 675, "loan_amount": 53377, "year": "1998"}, {"count": 333, "loan_amount": 28212, "year": "1999"}, {"count": 196, "loan_amount": 17444, "year": "2000"}, {"count": 788, "loan_amount": 75192, "year": "2001"}, {"count": 1045, "loan_amount": 101634, "year": "2002"}, {"count": 1566, "loan_amount": 156905, "year": "2003"}, {"count": 715, "loan_amount": 68482, "year": "2004"}, {"count": 516, "loan_amount": 51393, "year": "2005"}, {"count": 403, "loan_amount": 44271, "year": "2006"}, {"count": 359, "loan_amount": 38270, "year": "2007"}, {"count": 350, "loan_amount": 42916, "year": "2008"}, {"count": 655, "loan_amount": 87104, "year": "2009"}, {"count": 697, "loan_amount": 93660, "year": "2010"}, {"count": 558, "loan_amount": 74632, "year": "2011"}, {"count": 786, "loan_amount": 125076, "year": "2012"}, {"count": 460, "loan_amount": 68147, "year": "2013"}, {"count": 744, "loan_amount": 121476, "year": "2014"}]}, "FinancialInstitution": "Simmons First National Bank", "loanType": "refi", "location": "nationwide"}