{"type": "line", "data": {"years": [{"count": 1, "loan_amount": 126, "year": "1990"}, {"count": 6, "loan_amount": 94, "year": "1996"}, {"count": 16, "loan_amount": 603, "year": "1997"}, {"count": 23, "loan_amount": 263, "year": "1998"}, {"count": 11, "loan_amount": 344, "year": "1999"}, {"count": 957, "loan_amount": 10023, "year": "2000"}, {"count": 1515, "loan_amount": 15186, "year": "2001"}, {"count": 628, "loan_amount": 5978, "year": "2002"}, {"count": 76, "loan_amount": 8666, "year": "2003"}, {"count": 68, "loan_amount": 16449, "year": "2004"}, {"count": 38, "loan_amount": 7041, "year": "2005"}, {"count": 40, "loan_amount": 10984, "year": "2006"}, {"count": 33, "loan_amount": 12313, "year": "2007"}, {"count": 18, "loan_amount": 4304, "year": "2008"}]}, "FinancialInstitution": "Chevy Chase Bank Fsb", "loanType": "all", "location": "01"}