{"type": "line", "data": {"years": [{"count": 292, "loan_amount": 2967, "year": "1990"}, {"count": 344, "loan_amount": 3068, "year": "1991"}, {"count": 268, "loan_amount": 2484, "year": "1992"}, {"count": 203, "loan_amount": 1445, "year": "1993"}, {"count": 318, "loan_amount": 2771, "year": "1994"}, {"count": 314, "loan_amount": 3475, "year": "1995"}, {"count": 300, "loan_amount": 3572, "year": "1996"}, {"count": 108, "loan_amount": 1444, "year": "1997"}, {"count": 758, "loan_amount": 13876, "year": "1998"}, {"count": 1197, "loan_amount": 33141, "year": "1999"}, {"count": 1899, "loan_amount": 60411, "year": "2000"}, {"count": 2343, "loan_amount": 82260, "year": "2001"}, {"count": 1731, "loan_amount": 60936, "year": "2002"}, {"count": 666, "loan_amount": 19492, "year": "2003"}, {"count": 582, "loan_amount": 13519, "year": "2004"}, {"count": 619, "loan_amount": 12848, "year": "2005"}, {"count": 770, "loan_amount": 16435, "year": "2006"}, {"count": 778, "loan_amount": 17043, "year": "2007"}, {"count": 596, "loan_amount": 12441, "year": "2008"}, {"count": 406, "loan_amount": 5672, "year": "2009"}, {"count": 586, "loan_amount": 8876, "year": "2010"}, {"count": 505, "loan_amount": 10366, "year": "2011"}, {"count": 664, "loan_amount": 13838, "year": "2012"}, {"count": 785, "loan_amount": 21646, "year": "2013"}, {"count": 682, "loan_amount": 18847, "year": "2014"}]}, "FinancialInstitution": "Ent Federal Credit Union", "loanType": "home-improvement", "location": "nationwide"}